{
    "name": "Estimativa de Hornung",
    "level": 1,
    "school": "Adivinhação",
    "castingTime": "2 recortadas ou trituradas, espelhos, etc.), nem pode ser",
    "duration": "Instantânea alteradas do seu estado natural (moedas, jóias, gemas",
    "range": "300 metros convocar gemas, cristais, metais, pérolas, etc.. Além disso,",
    "area": "Especial tomadas de posse de outra pessoa. Um único Conjurar",
    "description": "Componentes Mágicos será capaz de convocar três componentes por nível do mago. Eles podem ser três Hornung, um dos principais feiticeiros no campo da magia componentes diferentes ou múltiplos de um único selvagem (antes de seu desaparecimento intempestivo componente. As tentativas de invocar a partes do corpo de enquanto experimentava Vento Selvagem), desenvolveu um animal (tais como peles de morcego) produzem este feitiço para melhorar a precisão de suas estimativas. A resultados imprevisíveis. O DM deve rolar sobre a tabela magia oferece ao mago uma estimativa instantânea e abaixo. altamente precisa do número de pessoas ou objetos em um grupo. A área de efeito da magia é um grupo de uma classe D4 geral de objetos. Todos os objetos do grupo devem estar na Resultado área de efeito da magia e o grupo como um todo deve ser 1 - Componente desejado aparece. visível para o mago. O mago não precisa ver cada 2 - Componente não aparece. indivíduo no grupo, apenas os limites gerais de tamanho e 3 - Criatura é teleportada para o mago. a área do grupo. Por exemplo, um assistente em uma 4 - Mago é teleportado para a criatura. colina poderia olhar para baixo em uma floresta e estimar o número de árvores ao todo ou parte dela. Ele não pôde Só os animais com inteligência de 1-4 podem ser afetados obter uma estimativa do número de goblins dentro da por esta magia. Humanóides e animais fantásticos floresta, no entanto, em função de que o grupo como um (dragões, bugbears, unicórnios, etc.) não podem ser todo (goblins) está escondido da vista. A estimativa gerada afetados. Em todos os casos, o DM deve usar o bom senso é precisa para o maior fator de dez (arredondada). Por para determinar a probabilidade do componente sendo exemplo, se Estimativa de Hornung for expressa em um localizado no alcance da mágica. grupo de 439 cavaleiros, a estimativa seria 400. Se houvesse 2,670 cavaleiros, o mago estimaria 3.000. Se houvesse 37 cavaleiros, a resposta seria 40. Claramente,"
}