{
    "name": "Pedra em Lama",
    "level": 5,
    "school": "Alteração",
    "castingTime": "1",
    "duration": "Especial",
    "range": "10 metros/nível",
    "area": "Um cubo de 5 metros por nível",
    "description": "Essa magia transforma rocha natural de qualquer tipo em um volume equivalente de lodo. A profundidade do lodo não pode exceder metade de seu comprimento ou largura.\n\nCriaturas que não possam voar, levitar ou de outro modo fugir do lodo afundam a uma taxa de 3 metros por rodada e sufocam, exceto no caso de seres que sejam suficientemente leves para caminhar sobre esse tipo de terreno. Galhos e madeira podem ser usados como bóias, mas a quantidade necessária desses materiais é determinada pelo Mestre. O lodo permanece até que o inverso desta"
}
