{
    "name": "Tentáculos",
    "level": 6,
    "school": "Conjuração, Alteração",
    "castingTime": "1 rodada",
    "duration": "1 turno/nível",
    "range": "0",
    "area": "O mago",
    "description": "Através desta magia, o mago faz com que dois tentáculos esverdeados de 3 m de comprimento cresçam de seu corpo. Um tentáculo cresce em cada lado do corpo do mago, centralizado entre sua axila e sua coxa. O mago pode usar os tentáculos como membros normais para agarrar ferramentas, usar armas, ou ajudar numa escalada. Cada Tentáculo pode fazer um ata- que, efetivamente concedendo ao mago dois ataques extras por rodada; um Tentáculo pode atacar infligido 1d6 pontos de danos, ou ele pode empu- nhar uma espada, punhal ou outra arma (com a mesma habilidade do mago). Os tentáculos flexíveis podem atingir facilmente vítimas de qualquer lado do corpo do mago. Se um tentáculo desarmado faz um ataque bem-sucedido contra uma ví- tima do tamanho de um homem ou menor (menos de 2 m de altura), ele também agarra e segura a vítima para infligir automaticamente 2d4 pontos de dano em cada rodada subsequente. Para libertar-se, a vítima deve cortar o tentáculo; não há outro meio de liber- tar-se que não seja cortar o membro, matar o mago, ou anular a magia com Dissipar Magia. Um tentáculo é morto se levar 10 pontos de dano; danos diri- gidos para o tentáculo não têm efeitos prejudiciais sobre o mago. Um mago com os dois tentáculos intactos adiciona um bônus de 40% a sua taxa de sucesso em montanhismo (ver página 84 do Livro do Jogador) e adiciona um modificador de 20%, se ele tem apenas um tentáculo intacto. O componente material para esta magia é um Tentáculo seco de um pe- queno polvo."
}