{
    "name": "Localizar Restos Mortais",
    "level": 1,
    "school": "Necromancia/Adivinhação",
    "castingTime": "1",
    "duration": "1 turno + 5 rodadas/nível",
    "range": "0",
    "components": "V, S, M",
    "area": "30' long + 5'/ nível",
    "savingThrow": "Não",
    "source": "The Complete Book of Necromancers (AD&D 2ª Ed.)",
    "description": "Descrição\n\nThis spell attunes the caster to the physical remains of dead beings in the area of effect. Locate remains will\n\nthus easily detect the presence of unburied corpses or corporeal undead (such as skeletons, zombies, or ghasts), but has no effect on noncorporeal undead (such as ghosts or spectres). The area of effect extends in a 10' wide path, facing the in the caster's current direction. Scanning in a direction requires one round, during which time the caster remains motionless in concentration.\n\nLocate remains is mostly unaffected by walls or obstacles, though the area of effect is decreased (to 10' +\n\nIV level) by more than three feet of solid stone, ten feet of wood or packed earth, or one inch of metal.\n\nIn the most general application, the spell precisely locates any and all physical remains of individuals in the\n\narea of effect, regardless of sex, species, and undead status. This spell does not impart any knowledge regarding the identity (or undead nature) of the remains; only the current locations of corpses within the area of effect are learned. If a personal item or a small fragment of the deceased individual is available at the time of casting, the spell can be used to locate the remains of that specific individual. In that case, the spell docs not register the presence of any remains except those of the desired individual.\n\nBoth the general and specific versions of the spell have no effect if cast on a living creature of any kind.\n\nThe material component for this spell is either a small piece of bone from a human cadaver (for the general version) or else an article of clothing, personal possession, or strand of hair (for the specific version). This spell is popular in regions with strict burial customs."
}
